[{"line":2,"elements":[{"line":7,"name":"","description":"","type":"background","keyword":"Background","steps":[{"result":{"duration":999800,"status":"passed"},"line":8,"name":"que tengo una calculadora disponible","match":{"location":"com.pruebatecnica.stepdefinitions.CalculadoraSteps.que_tengo_una_calculadora_disponible()"},"keyword":"Given "}]},{"start_timestamp":"2025-12-19T22:38:44.028Z","line":10,"name":"Suma de dos números","description":"","id":"calculadora-básica;suma-de-dos-números","type":"scenario","keyword":"Scenario","steps":[{"result":{"duration":987800,"status":"passed"},"line":11,"name":"que ingreso el número 5","match":{"arguments":[{"val":"5","offset":22}],"location":"com.pruebatecnica.stepdefinitions.CalculadoraSteps.que_ingreso_el_numero(double)"},"keyword":"Given "},{"result":{"status":"passed"},"line":12,"name":"que ingreso el número 3","match":{"arguments":[{"val":"3","offset":22}],"location":"com.pruebatecnica.stepdefinitions.CalculadoraSteps.que_ingreso_el_numero(double)"},"keyword":"And "},{"result":{"status":"passed"},"line":13,"name":"realizo la operación suma","match":{"location":"com.pruebatecnica.stepdefinitions.CalculadoraSteps.realizo_la_operacion_suma()"},"keyword":"When "},{"result":{"duration":26996100,"status":"passed"},"line":14,"name":"el resultado debe ser 8","match":{"arguments":[{"val":"8","offset":22}],"location":"com.pruebatecnica.stepdefinitions.CalculadoraSteps.el_resultado_debe_ser(double)"},"keyword":"Then "}]}],"name":"Calculadora Básica","description":"  Como usuario de la calculadora\n  Quiero realizar operaciones matemáticas básicas\n  Para obtener resultados correctos\n ","id":"calculadora-básica","keyword":"Feature","uri":"classpath:features/calculadora.feature","tags":[]}]